odoo/addons/mgmtsystem_evaluation_hr/README.rst
odoo/addons/mgmtsystem_evaluation_hr/__init__.py
odoo/addons/mgmtsystem_evaluation_hr/__manifest__.py
odoo/addons/mgmtsystem_evaluation_hr/i18n/es.po
odoo/addons/mgmtsystem_evaluation_hr/i18n/it.po
odoo/addons/mgmtsystem_evaluation_hr/i18n/mgmtsystem_evaluation_hr.pot
odoo/addons/mgmtsystem_evaluation_hr/models/__init__.py
odoo/addons/mgmtsystem_evaluation_hr/models/hr_employee.py
odoo/addons/mgmtsystem_evaluation_hr/readme/CONTRIBUTORS.rst
odoo/addons/mgmtsystem_evaluation_hr/readme/DESCRIPTION.rst
odoo/addons/mgmtsystem_evaluation_hr/static/description/icon.png
odoo/addons/mgmtsystem_evaluation_hr/static/description/index.html
odoo/addons/mgmtsystem_evaluation_hr/views/hr_employee.xml
odoo14_addon_mgmtsystem_evaluation_hr-14.0.1.0.1.dev5.dist-info/METADATA
odoo14_addon_mgmtsystem_evaluation_hr-14.0.1.0.1.dev5.dist-info/WHEEL
odoo14_addon_mgmtsystem_evaluation_hr-14.0.1.0.1.dev5.dist-info/top_level.txt
odoo14_addon_mgmtsystem_evaluation_hr-14.0.1.0.1.dev5.dist-info/RECORD
