Metadata-Version: 2.1
Name: odoo14-addon-mgmtsystem-evaluation-hr
Version: 14.0.1.0.1.dev5
Summary: Allow to use evaluations on Employees
Home-page: https://github.com/OCA/management-system
Author: Dixmit,Odoo Community Association (OCA)
Author-email: support@odoo-community.org
License: AGPL-3
Platform: UNKNOWN
Classifier: Programming Language :: Python
Classifier: Framework :: Odoo
Classifier: Framework :: Odoo :: 14.0
Classifier: License :: OSI Approved :: GNU Affero General Public License v3
Requires-Python: >=3.6
Requires-Dist: odoo14-addon-mgmtsystem-evaluation
Requires-Dist: odoo <14.1dev,>=14.0a
